_FDTDStaggered3D_with_relaxation_double.cpython-310-darwin.so
_FDTDStaggered3D_with_relaxation_single.cpython-310-darwin.so
BabelViscoFDTD/H5pySimple.py
BabelViscoFDTD/PropagationModel.py
BabelViscoFDTD/PropagationModel2D.py
BabelViscoFDTD/StaggeredFDTD_2D_With_Relaxation_BASE.py
BabelViscoFDTD/StaggeredFDTD_2D_With_Relaxation_CUDA.py
BabelViscoFDTD/StaggeredFDTD_2D_With_Relaxation_METAL.py
BabelViscoFDTD/StaggeredFDTD_2D_With_Relaxation_OPENCL.py
BabelViscoFDTD/StaggeredFDTD_3D_With_Relaxation.py
BabelViscoFDTD/StaggeredFDTD_3D_With_Relaxation_BASE.py
BabelViscoFDTD/StaggeredFDTD_3D_With_Relaxation_CUDA.py
BabelViscoFDTD/StaggeredFDTD_3D_With_Relaxation_METAL.py
BabelViscoFDTD/StaggeredFDTD_3D_With_Relaxation_OPENCL.py
BabelViscoFDTD/__init__.py
BabelViscoFDTD/_gpu_kernel.c
BabelViscoFDTD/_gpu_kernel2D.c
BabelViscoFDTD/_indexing.h
BabelViscoFDTD/_indexing2D.h
BabelViscoFDTD/tools/Babel.metallib
BabelViscoFDTD/tools/RayleighAndBHTE.py
BabelViscoFDTD/tools/__init__.py
BabelViscoFDTD/tools/libBabelMetal.dylib
BabelViscoFDTD-1.0.5.dist-info/METADATA
BabelViscoFDTD-1.0.5.dist-info/WHEEL
BabelViscoFDTD-1.0.5.dist-info/top_level.txt
BabelViscoFDTD-1.0.5.dist-info/RECORD
