Metadata-Version: 2.1
Name: BabelViscoFDTD
Version: 1.0.5
Summary: GPU/CPU 3D FDTD solution of viscoelastic equation
Author-email: samuel.pichardo@ucalgary.ca
License: BSD License
Keywords: FDTD,CUDA,OpenCL,Metal,viscoelastic
Classifier: Programming Language :: Python :: 3
Classifier: License :: OSI Approved :: BSD License
Classifier: Operating System :: MacOS
Classifier: Operating System :: Microsoft :: Windows
Classifier: Operating System :: POSIX :: Linux
Requires-Dist: numpy
Requires-Dist: scipy
Requires-Dist: h5py
Requires-Dist: hdf5plugin
Requires-Dist: pydicom
Requires-Dist: pyopencl
